mocking_utils/__init__.py
mocking_utils/data_model.py
mocking_utils/mock_function.py
mocking_utils/mock_property.py
mocking_utils/mock_request.py
mocking_utils/utils.py
mocking_utils-1.2.1.dist-info/LICENSE
mocking_utils-1.2.1.dist-info/METADATA
mocking_utils-1.2.1.dist-info/WHEEL
mocking_utils-1.2.1.dist-info/top_level.txt
mocking_utils-1.2.1.dist-info/RECORD
