Metadata-Version: 2.1
Name: mocking-utils
Version: 1.2.1
Summary: Highly useful utilities for mocking execution flow during unit test execution.
Home-page: https://github.com/do-py-together/mocking-utils
Author: Tim Davis
Author-email: timdavis.3991@gmail.com
License: UNKNOWN
Keywords: development,OO
Platform: UNKNOWN
Classifier: Development Status :: 3 - Alpha
Classifier: Intended Audience :: Developers
Classifier: Topic :: Software Development :: Build Tools
Classifier: Operating System :: OS Independent
Classifier: License :: OSI Approved :: MIT License
Classifier: Programming Language :: Python
Classifier: Programming Language :: Python :: 2
Classifier: Programming Language :: Python :: 2.7
Classifier: Programming Language :: Python :: 3.7
Requires-Dist: more-itertools (==5.0.0)
